AUTHORS.rst
CONTRIBUTING.rst
HISTORY.rst
LICENSE
MANIFEST.in
README.rst
setup.cfg
setup.py
docs/Makefile
docs/authors.rst
docs/conf.py
docs/contributing.rst
docs/history.rst
docs/index.rst
docs/installation.rst
docs/make.bat
docs/readme.rst
docs/usage.rst
pychapter/__init__.py
pychapter/api.py
pychapter/conf.py
pychapter/decorators.py
pychapter.egg-info/PKG-INFO
pychapter.egg-info/SOURCES.txt
pychapter.egg-info/dependency_links.txt
pychapter.egg-info/entry_points.txt
pychapter.egg-info/not-zip-safe
pychapter.egg-info/requires.txt
pychapter.egg-info/top_level.txt
pychapter/file_providers/__init__.py
pychapter/file_providers/kat.py
pychapter/info_providers/__init__.py
pychapter/info_providers/omdb.py
pychapter/info_providers/thetvdb.py
pychapter/subs_providers/__init__.py
pychapter/subs_providers/addic7ed.py
tests/__init__.py
tests/test_pychapter.py