Metadata-Version: 1.1
Name: pychapter
Version: 1.0.2
Summary: TV Series management tool
Home-page: https://github.com/XayOn/pychapter
Author: David Francos Cuartero
Author-email: opensource@davidfrancos.net
License: ISCL
Keywords: pychapter
Platform: UNKNOWN
Classifier: Development Status :: 2 - Pre-Alpha
Classifier: Intended Audience :: Developers
Classifier: License :: OSI Approved :: ISC License (ISCL)
Classifier: Natural Language :: English
Classifier: Programming Language :: Python :: 3.5
